README.md
setup.py
very_simple_logger/__init__.py
very_simple_logger/very_simple_logger.py
very_simple_logger.egg-info/PKG-INFO
very_simple_logger.egg-info/SOURCES.txt
very_simple_logger.egg-info/dependency_links.txt
very_simple_logger.egg-info/requires.txt
very_simple_logger.egg-info/top_level.txt