Metadata-Version: 2.1
Name: very-simple-logger
Version: 0.1
Summary: Library to create a simple logger with a standard format.
Home-page: https://github.com/javierzurdo/Very_Simple_Logger
Author: Javier S. Zurdo
Classifier: Programming Language :: Python :: 3
Classifier: License :: OSI Approved :: MIT License
Classifier: Operating System :: OS Independent
Requires-Python: >=3.6
